networking_ovn/__init__.py
networking_ovn/_i18n.py
networking_ovn/ovn_db_sync.py
networking_ovn/version.py
networking_ovn/agent/__init__.py
networking_ovn/agent/metadata_agent.py
networking_ovn/agent/neutron_agent.py
networking_ovn/agent/metadata/__init__.py
networking_ovn/agent/metadata/agent.py
networking_ovn/agent/metadata/driver.py
networking_ovn/agent/metadata/ovsdb.py
networking_ovn/agent/metadata/server.py
networking_ovn/cmd/__init__.py
networking_ovn/cmd/migration_mtu.py
networking_ovn/cmd/neutron_ovn_db_sync_util.py
networking_ovn/cmd/eventlet/__init__.py
networking_ovn/cmd/eventlet/agents/__init__.py
networking_ovn/cmd/eventlet/agents/metadata.py
networking_ovn/common/__init__.py
networking_ovn/common/acl.py
networking_ovn/common/config.py
networking_ovn/common/constants.py
networking_ovn/common/exceptions.py
networking_ovn/common/extensions.py
networking_ovn/common/hash_ring_manager.py
networking_ovn/common/maintenance.py
networking_ovn/common/ovn_client.py
networking_ovn/common/utils.py
networking_ovn/common/client_extensions/__init__.py
networking_ovn/common/client_extensions/qos.py
networking_ovn/conf/__init__.py
networking_ovn/conf/agent/__init__.py
networking_ovn/conf/agent/metadata/__init__.py
networking_ovn/conf/agent/metadata/config.py
networking_ovn/db/__init__.py
networking_ovn/db/hash_ring.py
networking_ovn/db/head.py
networking_ovn/db/maintenance.py
networking_ovn/db/models.py
networking_ovn/db/revision.py
networking_ovn/db/migration/__init__.py
networking_ovn/db/migration/alembic_migrations/README
networking_ovn/db/migration/alembic_migrations/__init__.py
networking_ovn/db/migration/alembic_migrations/env.py
networking_ovn/db/migration/alembic_migrations/script.py.mako
networking_ovn/db/migration/alembic_migrations/versions/CONTRACT_HEAD
networking_ovn/db/migration/alembic_migrations/versions/EXPAND_HEAD
networking_ovn/db/migration/alembic_migrations/versions/initial_branchpoint.py
networking_ovn-7.4.1.dist-info/AUTHORS
networking_ovn-7.4.1.dist-info/LICENSE
networking_ovn-7.4.1.dist-info/METADATA
networking_ovn-7.4.1.dist-info/WHEEL
networking_ovn-7.4.1.dist-info/entry_points.txt
networking_ovn-7.4.1.dist-info/pbr.json
networking_ovn-7.4.1.dist-info/top_level.txt
networking_ovn-7.4.1.dist-info/RECORD
