Metadata-Version: 2.1
Name: networking-ovn
Version: 7.4.1
Summary: OpenStack Neutron integration with OVN
Home-page: https://docs.openstack.org/networking-ovn/latest/
Author: OpenStack
Author-email: openstack-discuss@lists.openstack.org
License: UNKNOWN
Platform: UNKNOWN
Classifier: Environment :: OpenStack
Classifier: Intended Audience :: Information Technology
Classifier: Intended Audience :: System Administrators
Classifier: License :: OSI Approved :: Apache Software License
Classifier: Operating System :: POSIX :: Linux
Classifier: Programming Language :: Python
Classifier: Programming Language :: Python :: 2
Classifier: Programming Language :: Python :: 2.7
Classifier: Programming Language :: Python :: 3
Classifier: Programming Language :: Python :: 3.6
Classifier: Programming Language :: Python :: 3.7
Requires-Dist: Babel (!=2.4.0,>=2.3.4)
Requires-Dist: SQLAlchemy (>=1.2.0)
Requires-Dist: futurist (>=1.2.0)
Requires-Dist: netaddr (>=0.7.18)
Requires-Dist: neutron-lib (>=1.28.0)
Requires-Dist: neutron (>=13.0.0.0b2)
Requires-Dist: octavia-lib (>=1.3.1)
Requires-Dist: oslo.config (>=5.2.0)
Requires-Dist: ovs (>=2.8.0)
Requires-Dist: ovsdbapp (>=0.17.0)
Requires-Dist: pbr (!=2.1.0,>=2.0.0)
Requires-Dist: pyOpenSSL (>=17.1.0)
Requires-Dist: requests (>=2.14.2)
Requires-Dist: six (>=1.12.0)
Requires-Dist: tenacity (>=5.0.2)
Requires-Dist: tooz (>=1.58.0)
